impyrial/__init__.py
impyrial/utils.py
impyrial/length/__init__.py
impyrial/length/api.py
impyrial/length/core.py
impyrial/weight/__init__.py
impyrial/weight/api.py
impyrial/weight/core.py
impyrial_uyen99-0.1.1.dist-info/LICENSE
impyrial_uyen99-0.1.1.dist-info/METADATA
impyrial_uyen99-0.1.1.dist-info/WHEEL
impyrial_uyen99-0.1.1.dist-info/top_level.txt
impyrial_uyen99-0.1.1.dist-info/RECORD
