Metadata-Version: 2.1
Name: impyrial_uyen99
Version: 0.1.1
Summary: A package for converting impyiral lengths and weights.
Author: uyenhoang99
Requires-Python: >=2.7
License-File: LICENSE
Requires-Dist: pandas
Requires-Dist: scipy
Requires-Dist: matplotlib
